{"_id":"SyHNscFk7","title":"QML","dateCreated":1527520045253,"lastAccessed":"2018-05-28T15:07:25.254Z","lastUpdated":"2018-05-28T15:09:26.534Z","notebookId":"Sy-B-uTw1m","body":{"blocks":[{"key":"ag6qs","text":"QML","type":"header-one","depth":0,"inlineStyleRanges":[],"entityRanges":[],"data":{}},{"key":"b2ipm","text":"Learning QML ","type":"unstyled","depth":0,"inlineStyleRanges":[],"entityRanges":[],"data":{}},{"key":"7ub7g","text":"A few months ago I had the passion for laboratory","type":"unstyled","depth":0,"inlineStyleRanges":[],"entityRanges":[],"data":{}},{"key":"ek1ci","text":"Today I go metting again","type":"unstyled","depth":0,"inlineStyleRanges":[],"entityRanges":[],"data":{}},{"key":"du17o","text":"","type":"unstyled","depth":0,"inlineStyleRanges":[],"entityRanges":[],"data":{}},{"key":"6dpra","text":"QML ","type":"unstyled","depth":0,"inlineStyleRanges":[],"entityRanges":[],"data":{}},{"key":"4podj","text":"","type":"unstyled","depth":0,"inlineStyleRanges":[],"entityRanges":[],"data":{}},{"key":"bliih","text":"QBS file","type":"unstyled","depth":0,"inlineStyleRanges":[],"entityRanges":[],"data":{}},{"key":"cqn02","text":"sudo apt-get install qbs","type":"custom-code-block-bash","depth":0,"inlineStyleRanges":[],"entityRanges":[],"data":{}},{"key":"4n7mi","text":"","type":"unstyled","depth":0,"inlineStyleRanges":[],"entityRanges":[],"data":{}},{"key":"e1n87","text":"Qbs is a build automation tool designed to conveniently manage the build process of software projects across multiple platforms. ","type":"unstyled","depth":0,"inlineStyleRanges":[],"entityRanges":[],"data":{}},{"key":"146rn","text":" Not Working for now :(","type":"unstyled","depth":0,"inlineStyleRanges":[],"entityRanges":[],"data":{}},{"key":"8bfki","text":" ","type":"unstyled","depth":0,"inlineStyleRanges":[],"entityRanges":[],"data":{}},{"key":"5bqfr","text":" Estructura basica de un archivo QML","type":"header-two","depth":0,"inlineStyleRanges":[],"entityRanges":[],"data":{}},{"key":"ebe21","text":" ","type":"header-one","depth":0,"inlineStyleRanges":[],"entityRanges":[],"data":{}}],"entityMap":{}},"tags":["favorite"],"shareId":"BkIss5tyQ"}
